nonebot_plugin_helltide-0.1.7.dist-info/METADATA
nonebot_plugin_helltide-0.1.7.dist-info/WHEEL
nonebot_plugin_helltide-0.1.7.dist-info/licenses/LICENSE
nonebot_plugin_helltide/.gitignore
nonebot_plugin_helltide/__init__.py
nonebot_plugin_helltide/config.py
nonebot_plugin_helltide-0.1.7.dist-info/RECORD
