Metadata-Version: 2.1
Name: nonebot-plugin-helltide
Version: 0.1.7
Summary: Diablo 4 Helltide Event Tracker work with nonebot2
Home-page: https://github.com/QBkira/nonebot-plugin-helltide
Author-Email: qbkira <qbuouo@gmail.com>
License: MIT
Project-URL: Homepage, https://github.com/QBkira/nonebot-plugin-helltide
Project-URL: Repository, https://github.com/QBkira/nonebot-plugin-helltide/tree/master/nonebot_plugin_helltide
Project-URL: Documentation, https://github.com/QBkira/nonebot-plugin-helltide#readme
Requires-Python: >=3.8
Requires-Dist: nonebot2
Requires-Dist: nonebot2[fastapi]
Requires-Dist: pydantic
Requires-Dist: aiohttp
Requires-Dist: aiofiles
Requires-Dist: httpx
Requires-Dist: nonebot-adapter-onebot
Requires-Dist: nonebot-plugin-apscheduler
